django_ulogin/__init__.py
django_ulogin/exceptions.py
django_ulogin/forms.py
django_ulogin/locale/ru/LC_MESSAGES/django.mo
django_ulogin/locale/ru/LC_MESSAGES/django.po
django_ulogin/migrations/0001_initial.py
django_ulogin/migrations/__init__.py
django_ulogin/models.py
django_ulogin/settings.py
django_ulogin/signals.py
django_ulogin/templates/django_ulogin/confirm_delete.html
django_ulogin/templates/django_ulogin/error.html
django_ulogin/templates/django_ulogin/identities.html
django_ulogin/templates/django_ulogin/ulogin_media.html
django_ulogin/templates/django_ulogin/ulogin_widget.html
django_ulogin/templates/django_ulogin/ulogin_xd.html
django_ulogin/templatetags/__init__.py
django_ulogin/templatetags/ulogin_tags.py
django_ulogin/tests/__init__.py
django_ulogin/tests/identities.py
django_ulogin/tests/templatetags.py
django_ulogin/tests/urls.py
django_ulogin/urls.py
django_ulogin/views.py
django_ulogin-1.1.1.dist-info/LICENSE
django_ulogin-1.1.1.dist-info/WHEEL
django_ulogin-1.1.1.dist-info/METADATA
django_ulogin-1.1.1.dist-info/RECORD
