Metadata-Version: 2.1
Name: django-ulogin
Version: 1.1.1
Summary: User social authentication with ulogin.ru service
License: MIT
Author: Mikhail Porokhovnichenko
Author-email: marazmiki@gmail.com
Requires-Python: >=3.5,<4.0
Classifier: License :: OSI Approved :: MIT License
Classifier: Programming Language :: Python :: 3
Classifier: Programming Language :: Python :: 3.5
Classifier: Programming Language :: Python :: 3.6
Classifier: Programming Language :: Python :: 3.7
Classifier: Programming Language :: Python :: 3.8
Requires-Dist: requests (>=2.24.0,<3.0.0)
